langstream/__init__.py
langstream/api.py
langstream/util.py
langstream_ai-0.6.2.dist-info/LICENSE
langstream_ai-0.6.2.dist-info/METADATA
langstream_ai-0.6.2.dist-info/WHEEL
langstream_ai-0.6.2.dist-info/RECORD
